{
  "updateTime": "2025-01-26 15:42:53",
  "total": 50,
  "allItems": [
    {
      "source": "教学运行",
      "title": "关于2024—2025学年第一学期本科课程补考(缓考)考试安排的通知",
      "url": "http://jwc.cuit.edu.cn/info/1171/3190.htm",
      "date": "2025-01-21"
    },
    {
      "source": "新闻中心通知公告",
      "title": "关于2025年寒假期间两校区食堂（餐厅）餐饮供应的通知",
      "url": "http://www.cuit.edu.cn/info/1006/14002.htm",
      "date": "2025-01-15"
    },
    {
      "source": "新闻中心通知公告",
      "title": "关于2025年寒假期间交通车安排的通知",
      "url": "http://www.cuit.edu.cn/info/1006/13993.htm",
      "date": "2025-01-13"
    },
    {
      "source": "新闻中心通知公告",
      "title": "成都信息工程大学关于启动因地震灾害导致家庭经济困难专项资助工作的通知",
      "url": "http://www.cuit.edu.cn/info/1006/13974.htm",
      "date": "2025-01-08"
    },
    {
      "source": "教学运行",
      "title": "2024-2025学年第二学期选课通知",
      "url": "http://jwc.cuit.edu.cn/info/1173/3188.htm",
      "date": "2024-12-26"
    },
    {
      "source": "教学运行",
      "title": "关于2025年元旦节放假停课的通知",
      "url": "http://jwc.cuit.edu.cn/info/1172/3187.htm",
      "date": "2024-12-24"
    },
    {
      "source": "教学运行",
      "title": "关于2025年上半年全国计算机等级考试报名的通知",
      "url": "http://jwc.cuit.edu.cn/info/1174/3186.htm",
      "date": "2024-12-24"
    },
    {
      "source": "新闻中心通知公告",
      "title": "成都信息工程大学龙泉校区学生食堂一楼餐饮服务技术合作项目",
      "url": "http://www.cuit.edu.cn/info/1006/13880.htm",
      "date": "2024-12-23"
    },
    {
      "source": "新闻中心通知公告",
      "title": "关于学校2024年度辅导员考核结果的公示",
      "url": "http://www.cuit.edu.cn/info/1006/13862.htm",
      "date": "2024-12-20"
    },
    {
      "source": "学生处-公示栏",
      "title": "关于学校2024年度辅导员考核结果的公示",
      "url": "http://xsgzc.cuit.edu.cn/info/1090/1685.htm",
      "date": "2024-12-20"
    },
    {
      "source": "教学运行",
      "title": "成都信息工程大学2024-2025学年第一学期普通本科学生期末考试与寒假安排的通知",
      "url": "http://jwc.cuit.edu.cn/info/1171/3184.htm",
      "date": "2024-12-19"
    },
    {
      "source": "通知公告",
      "title": "学校2024年课堂教学改革优秀案例评选结果公示",
      "url": "http://jwc.cuit.edu.cn/info/1161/3183.htm",
      "date": "2024-12-19"
    },
    {
      "source": "学生处-公示栏",
      "title": "成都信息工程大学心理健康教育网站设计询价结果公示",
      "url": "http://xsgzc.cuit.edu.cn/info/1090/1684.htm",
      "date": "2024-12-18"
    },
    {
      "source": "新闻中心通知公告",
      "title": "成都信息工程大学第六届“教学质量奖”拟获奖人选公示",
      "url": "http://www.cuit.edu.cn/info/1006/13834.htm",
      "date": "2024-12-17"
    },
    {
      "source": "通知公告",
      "title": "成都信息工程大学2025年春季学期 辅修专业、微专业招生报名通知",
      "url": "http://jwc.cuit.edu.cn/info/1161/3171.htm",
      "date": "2024-12-13"
    },
    {
      "source": "教学运行",
      "title": "关于因研究生招生考试两校区停课的通知",
      "url": "http://jwc.cuit.edu.cn/info/1172/3168.htm",
      "date": "2024-12-12"
    },
    {
      "source": "新闻中心通知公告",
      "title": "成都信息工程大学教育基金会第八届“长虹双创基金”拟资助名单公示",
      "url": "http://www.cuit.edu.cn/info/1006/13767.htm",
      "date": "2024-12-12"
    },
    {
      "source": "教学运行",
      "title": "2024年下半年全国大学英语四、六级考试试音时间安排的通知",
      "url": "http://jwc.cuit.edu.cn/info/1174/3158.htm",
      "date": "2024-12-10"
    },
    {
      "source": "新闻中心通知公告",
      "title": "关于举办成都信息工程大学第十五届“挑战杯” 大学生课外学术科技作品竞赛的通知",
      "url": "http://www.cuit.edu.cn/info/1006/13735.htm",
      "date": "2024-12-10"
    },
    {
      "source": "新闻中心通知公告",
      "title": "成都信息工程大学2023-2024学年研究生评优拟获奖学生名单公示",
      "url": "http://www.cuit.edu.cn/info/1006/13726.htm",
      "date": "2024-12-09"
    },
    {
      "source": "学生处-公示栏",
      "title": "成都信息工程大学2023-2024学年研究生评优拟获奖学生名单公示",
      "url": "http://xsgzc.cuit.edu.cn/info/1090/1660.htm",
      "date": "2024-12-09"
    },
    {
      "source": "通知公告",
      "title": "技术赋能教育 教育塑造未来——沈火明为教师作“AI赋能教育教学与课程建设改革创新”专题培训",
      "url": "http://jwc.cuit.edu.cn/info/1161/3159.htm",
      "date": "2024-12-06"
    },
    {
      "source": "新闻中心通知公告",
      "title": "“英语能力提升”微专业2025年春季招生简章",
      "url": "http://www.cuit.edu.cn/info/1006/13715.htm",
      "date": "2024-12-06"
    },
    {
      "source": "新闻中心通知公告",
      "title": "成都信息工程大学2023-2024学年优良学风班评选结果公示",
      "url": "http://www.cuit.edu.cn/info/1006/13710.htm",
      "date": "2024-12-05"
    },
    {
      "source": "新闻中心通知公告",
      "title": "成都信息工程大学2024年12月公开招聘非事业编制（人事代理）工作人员公告",
      "url": "http://www.cuit.edu.cn/info/1006/13709.htm",
      "date": "2024-12-05"
    },
    {
      "source": "学生处-公示栏",
      "title": "成都信息工程大学2023-2024学年优良学风班评选结果公示",
      "url": "http://xsgzc.cuit.edu.cn/info/1090/1655.htm",
      "date": "2024-12-05"
    },
    {
      "source": "新闻中心通知公告",
      "title": "关于2024年12月6日至8日航空港校区1教和4教学楼断网的通知",
      "url": "http://www.cuit.edu.cn/info/1006/13701.htm",
      "date": "2024-12-04"
    },
    {
      "source": "新闻中心通知公告",
      "title": "关于图书馆试行座位预约服务的通知",
      "url": "http://www.cuit.edu.cn/info/1006/13695.htm",
      "date": "2024-12-04"
    },
    {
      "source": "教学运行",
      "title": "2024年下半年中小学教师资格考试成都信息工程大学考点考前公告",
      "url": "http://jwc.cuit.edu.cn/info/1174/3156.htm",
      "date": "2024-12-02"
    },
    {
      "source": "新闻中心通知公告",
      "title": "关于2024年12月校领导接待日安排的通知",
      "url": "http://www.cuit.edu.cn/info/1006/13675.htm",
      "date": "2024-11-29"
    },
    {
      "source": "通知公告",
      "title": "关于2024年下半年中小学教师资格考试面试考官安排的通知",
      "url": "http://jwc.cuit.edu.cn/info/1161/3153.htm",
      "date": "2024-11-28"
    },
    {
      "source": "通知公告",
      "title": "学校国产化技术体系师资培训班顺利结业",
      "url": "http://jwc.cuit.edu.cn/info/1161/3150.htm",
      "date": "2024-11-27"
    },
    {
      "source": "学生处-公示栏",
      "title": "成都信息工程大学2025届四川省优秀毕业生初审名单公示",
      "url": "http://xsgzc.cuit.edu.cn/info/1090/1651.htm",
      "date": "2024-11-26"
    },
    {
      "source": "通知公告",
      "title": "关于学校2024年本科优秀教材奖拟奖励名单的公示",
      "url": "http://jwc.cuit.edu.cn/info/1161/3148.htm",
      "date": "2024-11-25"
    },
    {
      "source": "学生处-公示栏",
      "title": "2024年本科生筑梦奖学金拟获奖学生公示",
      "url": "http://xsgzc.cuit.edu.cn/info/1090/1646.htm",
      "date": "2024-11-22"
    },
    {
      "source": "学生处-公示栏",
      "title": "成都信息工程大学2023-2024学年普通本科学生评奖评优拟获奖学生名单公示",
      "url": "http://xsgzc.cuit.edu.cn/info/1090/1645.htm",
      "date": "2024-11-22"
    },
    {
      "source": "通知公告",
      "title": "关于“成都信息工程大学教务处文化墙、教育教学宣传展板设计制作服务”项目终止的公告",
      "url": "http://jwc.cuit.edu.cn/info/1161/3138.htm",
      "date": "2024-11-21"
    },
    {
      "source": "通知公告",
      "title": "学校国产化技术体系师资培训正式开班",
      "url": "http://jwc.cuit.edu.cn/info/1161/3128.htm",
      "date": "2024-11-21"
    },
    {
      "source": "教学运行",
      "title": "关于2024年下半年全国大学英语四、六级口试考前模拟测试的通知",
      "url": "http://jwc.cuit.edu.cn/info/1174/3122.htm",
      "date": "2024-11-20"
    },
    {
      "source": "通知公告",
      "title": "成都信息工程大学询价函",
      "url": "http://jwc.cuit.edu.cn/info/1161/3127.htm",
      "date": "2024-11-20"
    },
    {
      "source": "通知公告",
      "title": "我校参加第62届中国高等教育博览会",
      "url": "http://jwc.cuit.edu.cn/info/1161/3125.htm",
      "date": "2024-11-19"
    },
    {
      "source": "通知公告",
      "title": "2024-2025学年第二学期学生自主选课试点课程任课教师介绍",
      "url": "http://jwc.cuit.edu.cn/info/1161/3089.htm",
      "date": "2024-11-15"
    },
    {
      "source": "教学运行",
      "title": "关于第九届气象观测职业技能竞赛期间部分机房停课的通知",
      "url": "http://jwc.cuit.edu.cn/info/1172/3068.htm",
      "date": "2024-11-14"
    },
    {
      "source": "学生处-公示栏",
      "title": "成都信息工程大学2024年国家励志奖学金（第二批次）拟获奖学生名单公示",
      "url": "http://xsgzc.cuit.edu.cn/info/1090/1633.htm",
      "date": "2024-11-14"
    },
    {
      "source": "学生处-公示栏",
      "title": "成都信息工程大学2024年研究生国家奖学金第二批次拟获奖学生初审名单公示",
      "url": "http://xsgzc.cuit.edu.cn/info/1090/1632.htm",
      "date": "2024-11-14"
    },
    {
      "source": "学生处-公示栏",
      "title": "成都信息工程大学2023-2024学年本科生国家奖学金第二批次拟获奖学生初审名单公示",
      "url": "http://xsgzc.cuit.edu.cn/info/1090/1631.htm",
      "date": "2024-11-14"
    },
    {
      "source": "教学运行",
      "title": "关于2024年下半年全国大学英语四、六级考试准考证打印及注意事项的通知",
      "url": "http://jwc.cuit.edu.cn/info/1174/3059.htm",
      "date": "2024-11-11"
    },
    {
      "source": "教学运行",
      "title": "关于2024年9月全国计算机等级考试成绩、证书查询的通知",
      "url": "http://jwc.cuit.edu.cn/info/1174/3058.htm",
      "date": "2024-11-07"
    },
    {
      "source": "通知公告",
      "title": "我校9部教材入选四川省“十四五”普通高等教育本科规划教材",
      "url": "http://jwc.cuit.edu.cn/info/1161/3057.htm",
      "date": "2024-11-05"
    },
    {
      "source": "通知公告",
      "title": "关于开展成都信息工程大学教育基金会第八届“长虹双创基金”评选工作的通知",
      "url": "http://jwc.cuit.edu.cn/info/1161/3055.htm",
      "date": "2024-10-30"
    }
  ]
}